pytest_sigil/__init__.py
pytest_sigil/_plugin.py
pytest_sigil/py.typed
pytest_sigil-1.0.0.dist-info/METADATA
pytest_sigil-1.0.0.dist-info/WHEEL
pytest_sigil-1.0.0.dist-info/entry_points.txt
pytest_sigil-1.0.0.dist-info/RECORD
