Metadata-Version: 2.4
Name: pytest-sigil
Version: 1.0.0
Summary: Proper fixture resource cleanup by handling signals
License: MIT
Author: lovetheguitar
Author-email: entry.force.0p@icloud.com 
Maintainer: lovetheguitar
Maintainer-email: entry.force.0p@icloud.com 
Requires-Python: >=3.10,<4.0
Classifier: License :: OSI Approved :: MIT License
Classifier: Programming Language :: Python :: 3
Classifier: Programming Language :: Python :: 3.10
Classifier: Programming Language :: Python :: 3.11
Classifier: Programming Language :: Python :: 3.12
Classifier: Programming Language :: Python :: 3.13
Classifier: Programming Language :: Python :: 3.14
Requires-Dist: pytest (>=7.0.0,<9.0.0)
Project-URL: Homepage, https://github.com/hey-works/pytest-sigil
